{
  "title": "五群闲聊的一天，大家都在聊什么？",
  "subtitle": "2026-03-10 群聊日报",
  "summary": "昨天群里一共 428 条消息，大家主要在聊版本更新、联机问题和梗图，晚饭后最热闹。",
  "metrics": [
    {"label": "总消息数", "value": "428", "note": "来自昨日原始群消息"},
    {"label": "活跃人数", "value": "37", "note": "按实际发言人数统计"},
    {"label": "最高峰时段", "value": "20:00", "note": "该小时 61 条"},
    {"label": "活跃跨度", "value": "09:00-23:00", "note": "全天持续有人说话"}
  ],
  "timeline": [0,0,0,0,0,0,1,2,3,12,10,15,18,11,20,16,14,21,27,35,61,54,43,15],
  "insights": [
    "白天话题比较分散，晚上明显集中到版本和联机问题",
    "有几位核心成员持续接话，带动了整体节奏",
    "梗图和短句互动很多，聊天氛围偏轻松"
  ],
  "topics": [
    {"title": "版本更新", "summary": "大家围绕新版本改动、兼容性和体验差异展开了持续讨论。"},
    {"title": "联机问题", "summary": "多人提到联机卡顿、掉线和进房失败，交流了各自遇到的情况。"},
    {"title": "梗图接龙", "summary": "中间穿插了不少图片和短句互动，把整体氛围拉得更轻松。"},
    {"title": "模组推荐", "summary": "有人顺手安利了几个常用模组，也有人问了配置建议。"}
  ],
  "activeUsers": [
    {"name": "风", "count": 46, "summary": "昨天既在答问题，也在顺手接梗，存在感很强。"},
    {"name": "何意味", "count": 41, "summary": "主要在版本和联机话题里接话，输出频率很稳定。"},
    {"name": "Alicia", "count": 32, "summary": "多次补充自己的实测体验，推动了问题定位。"},
    {"name": "Mio", "count": 27, "summary": "更偏向轻松互动，表情和短句很多。"}
  ],
  "quotes": [
    {"speaker": "风", "text": "你这不是卡，是大家都在抢房主"},
    {"speaker": "何意味", "text": "这个更新看着小，结果把一堆旧习惯都掀了"},
    {"speaker": "Mio", "text": "先别急着重装，你把模组表发一下"}
  ],
  "footerNote": "本日报由前一天的原始群聊消息自动整理生成，内容会尽量忠于当天聊天本身。"
}
